<?xml version='1.0' encoding='UTF-8'?>
<categories>
    <category>
        <name>Periféricos</name>
    </category>
    <category>
        <name>Placas de circuitos</name>
    </category>
    <category>
        <name>Baterias e Pilhas</name>
    </category>
    <category>
        <name>Fios</name>
    </category>
    <category>
        <name>Celulares</name>
    </category>
    <category>
        <name>Eletrodomésticos</name>
    </category>
    <category>
        <name>Rádios</name>
    </category>
    <category>
        <name>Televisores</name>
    </category>
    <category>
        <name>Outro tipo de categoria</name>
    </category>
</categories>